{"name":"Login with username and password","id":"login;login-with-username-and-password","testSteps":[{"number":1,"description":"1: Login with username and password ({email\u003d\"thaur@mail.com\", password\u003d\"thaurn\", result\u003d\"logged in\"})","duration":9484,"startTime":"2022-11-04T20:46:58.639475500+07:00[Asia/Jakarta]","result":"SUCCESS","precondition":false,"level":0,"lineNumber":14,"children":[{"number":2,"description":"Given I set login url","duration":684,"startTime":"2022-11-04T20:46:58.900075700+07:00[Asia/Jakarta]","result":"SUCCESS","precondition":false,"level":1},{"number":3,"description":"And I set \"thaur@mail.com\" and \"thaurn\"","duration":3858,"startTime":"2022-11-04T20:46:59.665273900+07:00[Asia/Jakarta]","result":"SUCCESS","precondition":false,"level":1},{"number":4,"description":"When I request post auth","duration":3402,"startTime":"2022-11-04T20:47:03.525276700+07:00[Asia/Jakarta]","result":"SUCCESS","precondition":false,"level":1,"children":[{"number":5,"description":"POST https://alta-shop.herokuapp.com/api/auth/login\r","duration":0,"startTime":"2022-11-04T20:47:06.920389100+07:00[Asia/Jakarta]","result":"SUCCESS","restQuery":{"method":"POST","path":"https://alta-shop.herokuapp.com/api/auth/login\r","content":"{\n    \"password\": \"thaurn\",\n    \"email\": \"thaur@mail.com\"\n}\r","contentType":"application/json","requestHeaders":"Accept\u003d*/*\r\n\t\t\t\tContent-Type\u003dapplication/json\r","requestCookies":"\r","responseHeaders":"Server: Cowboy\r\nConnection: keep-alive\r\nContent-Type: application/json\r\nDate: Fri, 04 Nov 2022 13:47:07 GMT\r\nContent-Length: 153\r\nVia: 1.1 vegur\r","responseCookies":"\r","responseBody":"{\n    \"data\": \"eyJhbGciOiJIUzI1NiIsInR5cCI6IkpXVCJ9.eyJGdWxsbmFtZSI6IlRoYXVyIiwiRW1haWwiOiJ0aGF1ckBtYWlsLmNvbSJ9.MQtDVCwaIvFycZV8nu32ZZEX55XGtlo-VkKpb1r-HaY\"\n}","statusCode":200},"precondition":false,"level":2}]},{"number":6,"description":"Then I get \"logged in\" as auth result","duration":1150,"startTime":"2022-11-04T20:47:06.942334100+07:00[Asia/Jakarta]","result":"SUCCESS","precondition":false,"level":1}]},{"number":7,"description":"2: Login with username and password ({email\u003d\"thaur@mail.com\", password\u003d\"pinto\", result\u003d\"invalid error\"})","duration":1470,"startTime":"2022-11-04T20:47:08.374024900+07:00[Asia/Jakarta]","result":"SUCCESS","precondition":false,"level":0,"lineNumber":15,"children":[{"number":8,"description":"Given I set login url","duration":8,"startTime":"2022-11-04T20:47:08.379011900+07:00[Asia/Jakarta]","result":"SUCCESS","precondition":false,"level":1},{"number":9,"description":"And I set \"thaur@mail.com\" and \"pinto\"","duration":16,"startTime":"2022-11-04T20:47:08.389980600+07:00[Asia/Jakarta]","result":"SUCCESS","precondition":false,"level":1},{"number":10,"description":"When I request post auth","duration":1402,"startTime":"2022-11-04T20:47:08.409929400+07:00[Asia/Jakarta]","result":"SUCCESS","precondition":false,"level":1,"children":[{"number":11,"description":"POST https://alta-shop.herokuapp.com/api/auth/login\r","duration":0,"startTime":"2022-11-04T20:47:09.808108200+07:00[Asia/Jakarta]","result":"SUCCESS","restQuery":{"method":"POST","path":"https://alta-shop.herokuapp.com/api/auth/login\r","content":"{\n    \"password\": \"pinto\",\n    \"email\": \"thaur@mail.com\"\n}\r","contentType":"application/json","requestHeaders":"Accept\u003d*/*\r\n\t\t\t\tContent-Type\u003dapplication/json\r","requestCookies":"\r","responseHeaders":"Server: Cowboy\r\nConnection: keep-alive\r\nContent-Type: application/json\r\nDate: Fri, 04 Nov 2022 13:47:10 GMT\r\nContent-Length: 41\r\nVia: 1.1 vegur\r","responseCookies":"\r","responseBody":"{\n    \"error\": \"email or password is invalid\"\n}","statusCode":400},"precondition":false,"level":2}]},{"number":12,"description":"Then I get \"invalid error\" as auth result","duration":26,"startTime":"2022-11-04T20:47:09.816086500+07:00[Asia/Jakarta]","result":"SUCCESS","precondition":false,"level":1}]},{"number":13,"description":"3: Login with username and password ({email\u003d\"user@mail.com\", password\u003d\"\", result\u003d\"password error\"})","duration":1586,"startTime":"2022-11-04T20:47:09.994845400+07:00[Asia/Jakarta]","result":"SUCCESS","precondition":false,"level":0,"lineNumber":16,"children":[{"number":14,"description":"Given I set login url","duration":15,"startTime":"2022-11-04T20:47:09.998835+07:00[Asia/Jakarta]","result":"SUCCESS","precondition":false,"level":1},{"number":15,"description":"And I set \"user@mail.com\" and \"\"","duration":5,"startTime":"2022-11-04T20:47:10.018781100+07:00[Asia/Jakarta]","result":"SUCCESS","precondition":false,"level":1},{"number":16,"description":"When I request post auth","duration":1502,"startTime":"2022-11-04T20:47:10.056681+07:00[Asia/Jakarta]","result":"SUCCESS","precondition":false,"level":1,"children":[{"number":17,"description":"POST https://alta-shop.herokuapp.com/api/auth/login\r","duration":0,"startTime":"2022-11-04T20:47:11.555913500+07:00[Asia/Jakarta]","result":"SUCCESS","restQuery":{"method":"POST","path":"https://alta-shop.herokuapp.com/api/auth/login\r","content":"{\n    \"password\": \"\",\n    \"email\": \"user@mail.com\"\n}\r","contentType":"application/json","requestHeaders":"Accept\u003d*/*\r\n\t\t\t\tContent-Type\u003dapplication/json\r","requestCookies":"\r","responseHeaders":"Server: Cowboy\r\nConnection: keep-alive\r\nContent-Type: application/json\r\nDate: Fri, 04 Nov 2022 13:47:12 GMT\r\nContent-Length: 33\r\nVia: 1.1 vegur\r","responseCookies":"\r","responseBody":"{\n    \"error\": \"password is required\"\n}","statusCode":400},"precondition":false,"level":2}]},{"number":18,"description":"Then I get \"password error\" as auth result","duration":18,"startTime":"2022-11-04T20:47:11.559903100+07:00[Asia/Jakarta]","result":"SUCCESS","precondition":false,"level":1}]},{"number":19,"description":"4: Login with username and password ({email\u003d\"\", password\u003d\"nasdade\", result\u003d\"email error\"})","duration":1473,"startTime":"2022-11-04T20:47:11.591816+07:00[Asia/Jakarta]","result":"SUCCESS","precondition":false,"level":0,"lineNumber":17,"children":[{"number":20,"description":"Given I set login url","duration":6,"startTime":"2022-11-04T20:47:11.594808500+07:00[Asia/Jakarta]","result":"SUCCESS","precondition":false,"level":1},{"number":21,"description":"And I set \"\" and \"nasdade\"","duration":7,"startTime":"2022-11-04T20:47:11.603785400+07:00[Asia/Jakarta]","result":"SUCCESS","precondition":false,"level":1},{"number":22,"description":"When I request post auth","duration":1425,"startTime":"2022-11-04T20:47:11.613759300+07:00[Asia/Jakarta]","result":"SUCCESS","precondition":false,"level":1,"children":[{"number":23,"description":"POST https://alta-shop.herokuapp.com/api/auth/login\r","duration":0,"startTime":"2022-11-04T20:47:13.038759800+07:00[Asia/Jakarta]","result":"SUCCESS","restQuery":{"method":"POST","path":"https://alta-shop.herokuapp.com/api/auth/login\r","content":"{\n    \"password\": \"nasdade\",\n    \"email\": \"\"\n}\r","contentType":"application/json","requestHeaders":"Accept\u003d*/*\r\n\t\t\t\tContent-Type\u003dapplication/json\r","requestCookies":"\r","responseHeaders":"Server: Cowboy\r\nConnection: keep-alive\r\nContent-Type: application/json\r\nDate: Fri, 04 Nov 2022 13:47:13 GMT\r\nContent-Length: 30\r\nVia: 1.1 vegur\r","responseCookies":"\r","responseBody":"{\n    \"error\": \"email is required\"\n}","statusCode":400},"precondition":false,"level":2}]},{"number":24,"description":"Then I get \"email error\" as auth result","duration":21,"startTime":"2022-11-04T20:47:13.041751+07:00[Asia/Jakarta]","result":"SUCCESS","precondition":false,"level":1}]},{"number":25,"description":"5: Login with username and password ({email\u003d\"naevis@mail.com\", password\u003d\"pass\", result\u003d\"user not found\"})","duration":1782,"startTime":"2022-11-04T20:47:13.079651400+07:00[Asia/Jakarta]","result":"SUCCESS","precondition":false,"level":0,"lineNumber":18,"children":[{"number":26,"description":"Given I set login url","duration":7,"startTime":"2022-11-04T20:47:13.082642600+07:00[Asia/Jakarta]","result":"SUCCESS","precondition":false,"level":1},{"number":27,"description":"And I set \"naevis@mail.com\" and \"pass\"","duration":2,"startTime":"2022-11-04T20:47:13.092614500+07:00[Asia/Jakarta]","result":"SUCCESS","precondition":false,"level":1},{"number":28,"description":"When I request post auth","duration":1746,"startTime":"2022-11-04T20:47:13.097602+07:00[Asia/Jakarta]","result":"SUCCESS","precondition":false,"level":1,"children":[{"number":29,"description":"POST https://alta-shop.herokuapp.com/api/auth/login\r","duration":0,"startTime":"2022-11-04T20:47:14.842130300+07:00[Asia/Jakarta]","result":"SUCCESS","restQuery":{"method":"POST","path":"https://alta-shop.herokuapp.com/api/auth/login\r","content":"{\n    \"password\": \"pass\",\n    \"email\": \"naevis@mail.com\"\n}\r","contentType":"application/json","requestHeaders":"Accept\u003d*/*\r\n\t\t\t\tContent-Type\u003dapplication/json\r","requestCookies":"\r","responseHeaders":"Server: Cowboy\r\nConnection: keep-alive\r\nContent-Type: application/json\r\nDate: Fri, 04 Nov 2022 13:47:15 GMT\r\nContent-Length: 29\r\nVia: 1.1 vegur\r","responseCookies":"\r","responseBody":"{\n    \"error\": \"record not found\"\n}","statusCode":400},"precondition":false,"level":2}]},{"number":30,"description":"Then I get \"user not found\" as auth result","duration":13,"startTime":"2022-11-04T20:47:14.846117700+07:00[Asia/Jakarta]","result":"SUCCESS","precondition":false,"level":1}]},{"number":31,"description":"6: Login with username and password ({email\u003d\"\", password\u003d\"\", result\u003d\"email error\"})","duration":1363,"startTime":"2022-11-04T20:47:14.872020300+07:00[Asia/Jakarta]","result":"SUCCESS","precondition":false,"level":0,"lineNumber":19,"children":[{"number":32,"description":"Given I set login url","duration":13,"startTime":"2022-11-04T20:47:14.875012100+07:00[Asia/Jakarta]","result":"SUCCESS","precondition":false,"level":1},{"number":33,"description":"And I set \"\" and \"\"","duration":3,"startTime":"2022-11-04T20:47:14.890975400+07:00[Asia/Jakarta]","result":"SUCCESS","precondition":false,"level":1},{"number":34,"description":"When I request post auth","duration":1324,"startTime":"2022-11-04T20:47:14.896954+07:00[Asia/Jakarta]","result":"SUCCESS","precondition":false,"level":1,"children":[{"number":35,"description":"POST https://alta-shop.herokuapp.com/api/auth/login\r","duration":0,"startTime":"2022-11-04T20:47:16.219985+07:00[Asia/Jakarta]","result":"SUCCESS","restQuery":{"method":"POST","path":"https://alta-shop.herokuapp.com/api/auth/login\r","content":"{\n    \"password\": \"\",\n    \"email\": \"\"\n}\r","contentType":"application/json","requestHeaders":"Accept\u003d*/*\r\n\t\t\t\tContent-Type\u003dapplication/json\r","requestCookies":"\r","responseHeaders":"Server: Cowboy\r\nConnection: keep-alive\r\nContent-Type: application/json\r\nDate: Fri, 04 Nov 2022 13:47:16 GMT\r\nContent-Length: 30\r\nVia: 1.1 vegur\r","responseCookies":"\r","responseBody":"{\n    \"error\": \"email is required\"\n}","statusCode":400},"precondition":false,"level":2}]},{"number":36,"description":"Then I get \"email error\" as auth result","duration":12,"startTime":"2022-11-04T20:47:16.221979900+07:00[Asia/Jakarta]","result":"SUCCESS","precondition":false,"level":1}]}],"userStory":{"id":"login","storyName":"Login","path":"Authentication/Login.feature","narrative":"  As a User\n  I want to login\n  So I can use the website","type":"feature"},"featureTag":{"name":"Authentication/Login","type":"feature","displayName":"Authentication/Login"},"title":"Login with username and password","description":"","tags":[{"name":"Authentication/Login","type":"feature","displayName":"Login"},{"name":"Authentication","type":"capability","displayName":"Authentication"}],"startTime":"2022-11-04T20:46:58.611552400+07:00[Asia/Jakarta]","duration":17626,"projectKey":"","isManualTestingUpToDate":false,"dataTable":{"headers":["email","password","result"],"rows":[{"values":["\"thaur@mail.com\"","\"thaurn\"","\"logged in\""],"lineNumber":14,"result":"SUCCESS"},{"values":["\"thaur@mail.com\"","\"pinto\"","\"invalid error\""],"lineNumber":15,"result":"SUCCESS"},{"values":["\"user@mail.com\"","\"\"","\"password error\""],"lineNumber":16,"result":"SUCCESS"},{"values":["\"\"","\"nasdade\"","\"email error\""],"lineNumber":17,"result":"SUCCESS"},{"values":["\"naevis@mail.com\"","\"pass\"","\"user not found\""],"lineNumber":18,"result":"SUCCESS"},{"values":["\"\"","\"\"","\"email error\""],"lineNumber":19,"result":"SUCCESS"}],"predefinedRows":true,"scenarioOutline":"Given I set login url\n\rAnd I set \u003cemail\u003e and \u003cpassword\u003e\n\rWhen I request post auth\n\rThen I get \u003cresult\u003e as auth result\n\r","dataSetDescriptors":[{"startRow":0,"rowCount":0,"name":"","description":""}]},"manual":false,"testSource":"Cucumber","result":"SUCCESS","scenarioOutline":"Given I set login url\r\nAnd I set \u003cemail\u003e and \u003cpassword\u003e\r\nWhen I request post auth\r\nThen I get \u003cresult\u003e as auth result"}